[
  {
    "playerId": "001",
    "playerName": "Mike Maignan",
    "playerPosition": "Goalkeeper",
    "playerNumber": "16",
    "playerImage": "https://img.a.transfermarkt.technology/portrait/header/182906-1681459155.jpg?lm=1"
  },
  {
    "playerId": "002",
    "playerName": "Sandro Tonali",
    "playerPosition": "Midfielder",
    "playerNumber": "8",
    "playerImage": "https://img.a.transfermarkt.technology/portrait/header/397033-1616775399.jpg?lm=1"
  },
  {
    "playerId": "003",
    "playerName": "Davide Calabria",
    "playerPosition": "Defender",
    "playerNumber": "2",
    "playerImage": "https://img.a.transfermarkt.technology/portrait/header/262523-1595926678.jpg?lm=1"
  },
  {
    "playerId": "004",
    "playerName": "Zlatan Ibrahimovic",
    "playerPosition": "Forward",
    "playerNumber": "11",
    "playerImage": "https://img.a.transfermarkt.technology/portrait/header/3455-1579506060.jpg?lm=1"
  }
]
